{
    "TERMINAL": "T39",
    "SEGMENTO": "GRAO",
    "PATIO": "PCX",
    "ATIVOS": [],
    "DATA": "2024-10-03",
    "SUBIDA": {
        "RUMO": {
            "GRAO": {
                "SALDO_VIRADA": 0,
                "SALDO_NAVEGACAO": [
                    0,
                    0,
                    0,
                    78,
                    65,
                    52,
                    39,
                    26,
                    13,
                    0,
                    0,
                    83,
                    70,
                    57,
                    44,
                    31,
                    18,
                    5,
                    0,
                    0,
                    84,
                    71,
                    58,
                    45
                ],
                "GERACAO_DE_VAZIOS": [
                    0,
                    0,
                    0,
                    0,
                    13,
                    13,
                    13,
                    13,
                    13,
                    13,
                    0,
                    0,
                    13,
                    13,
                    13,
                    13,
                    13,
                    13,
                    5,
                    0,
                    0,
                    13,
                    13,
                    13
                ],
                "GERACAO_EDITADA": [
                    0,
                    0,
                    0,
                    0,
                    0,
                    0,
                    0,
                    0,
                    0,
                    0,
                    0,
                    0,
                    0,
                    0,
                    0,
                    0,
                    0,
                    0,
                    0,
                    0,
                    0,
                    0,
                    0,
                    0
                ],
                "ALIVIO_DE_VAZIOS": [
                    0,
                    0,
                    0,
                    0,
                    0,
                    0,
                    0,
                    0,
                    0,
                    0,
                    0,
                    0,
                    0,
                    0,
                    0,
                    0,
                    0,
                    0,
                    0,
                    0,
                    0,
                    0,
                    0,
                    0
                ],
                "ALIVIO_EDITADO": [
                    0,
                    0,
                    0,
                    0,
                    0,
                    0,
                    0,
                    0,
                    0,
                    0,
                    0,
                    0,
                    0,
                    0,
                    0,
                    0,
                    0,
                    0,
                    0,
                    0,
                    0,
                    0,
                    0,
                    0
                ],
                "SALDO_DE_VAZIOS": [
                    271,
                    271,
                    271,
                    271,
                    284,
                    297,
                    310,
                    323,
                    336,
                    349,
                    349,
                    349,
                    362,
                    375,
                    388,
                    401,
                    414,
                    427,
                    432,
                    432,
                    432,
                    445,
                    458,
                    471
                ],
                "SATURACAO_VAZIO": {
                    "MIN": 0,
                    "MAX": 0
                }
            }
        },
        "MRS": {
            "GRAO": {
                "SALDO_VIRADA": 0,
                "SALDO_NAVEGACAO": [
                    0,
                    0,
                    0,
                    0,
                    0,
                    0,
                    0,
                    0,
                    0,
                    0,
                    0,
                    0,
                    0,
                    0,
                    0,
                    0,
                    0,
                    0,
                    0,
                    0,
                    0,
                    0,
                    0,
                    0
                ],
                "GERACAO_DE_VAZIOS": [
                    0,
                    0,
                    0,
                    0,
                    0,
                    0,
                    0,
                    0,
                    0,
                    0,
                    0,
                    0,
                    0,
                    0,
                    0,
                    0,
                    0,
                    0,
                    0,
                    0,
                    0,
                    0,
                    0,
                    0
                ],
                "GERACAO_EDITADA": [
                    0,
                    0,
                    0,
                    0,
                    0,
                    0,
                    0,
                    0,
                    0,
                    0,
                    0,
                    0,
                    0,
                    0,
                    0,
                    0,
                    0,
                    0,
                    0,
                    0,
                    0,
                    0,
                    0,
                    0
                ],
                "ALIVIO_DE_VAZIOS": [
                    0,
                    0,
                    0,
                    0,
                    0,
                    0,
                    0,
                    0,
                    0,
                    0,
                    0,
                    0,
                    0,
                    0,
                    0,
                    0,
                    0,
                    0,
                    0,
                    0,
                    0,
                    0,
                    0,
                    0
                ],
                "ALIVIO_EDITADO": [
                    0,
                    0,
                    0,
                    0,
                    0,
                    0,
                    0,
                    0,
                    0,
                    0,
                    0,
                    0,
                    0,
                    0,
                    0,
                    0,
                    0,
                    0,
                    0,
                    0,
                    0,
                    0,
                    0,
                    0
                ],
                "SALDO_DE_VAZIOS": [
                    0,
                    0,
                    0,
                    0,
                    0,
                    0,
                    0,
                    0,
                    0,
                    0,
                    0,
                    0,
                    0,
                    0,
                    0,
                    0,
                    0,
                    0,
                    0,
                    0,
                    0,
                    0,
                    0,
                    0
                ],
                "SATURACAO_VAZIO": {
                    "MIN": 0,
                    "MAX": 0
                }
            }
        },
        "VLI": {
            "GRAO": {
                "SALDO_VIRADA": 0,
                "SALDO_NAVEGACAO": [
                    0,
                    0,
                    0,
                    0,
                    0,
                    0,
                    0,
                    0,
                    0,
                    0,
                    0,
                    0,
                    0,
                    0,
                    0,
                    0,
                    0,
                    0,
                    0,
                    0,
                    0,
                    0,
                    0,
                    0
                ],
                "GERACAO_DE_VAZIOS": [
                    0,
                    0,
                    0,
                    0,
                    0,
                    0,
                    0,
                    0,
                    0,
                    0,
                    0,
                    0,
                    0,
                    0,
                    0,
                    0,
                    0,
                    0,
                    0,
                    0,
                    0,
                    0,
                    0,
                    0
                ],
                "GERACAO_EDITADA": [
                    0,
                    0,
                    0,
                    0,
                    0,
                    0,
                    0,
                    0,
                    0,
                    0,
                    0,
                    0,
                    0,
                    0,
                    0,
                    0,
                    0,
                    0,
                    0,
                    0,
                    0,
                    0,
                    0,
                    0
                ],
                "ALIVIO_DE_VAZIOS": [
                    0,
                    0,
                    0,
                    0,
                    0,
                    0,
                    0,
                    0,
                    0,
                    0,
                    0,
                    0,
                    0,
                    0,
                    0,
                    0,
                    0,
                    0,
                    0,
                    0,
                    0,
                    0,
                    0,
                    0
                ],
                "ALIVIO_EDITADO": [
                    0,
                    0,
                    0,
                    0,
                    0,
                    0,
                    0,
                    0,
                    0,
                    0,
                    0,
                    0,
                    0,
                    0,
                    0,
                    0,
                    0,
                    0,
                    0,
                    0,
                    0,
                    0,
                    0,
                    0
                ],
                "SALDO_DE_VAZIOS": [
                    0,
                    0,
                    0,
                    0,
                    0,
                    0,
                    0,
                    0,
                    0,
                    0,
                    0,
                    0,
                    0,
                    0,
                    0,
                    0,
                    0,
                    0,
                    0,
                    0,
                    0,
                    0,
                    0,
                    0
                ],
                "SATURACAO_VAZIO": {
                    "MIN": 0,
                    "MAX": 0
                }
            }
        }
    }
}