{
    "TERMINAL": "ADM",
    "SEGMENTO": "GRAO",
    "PATIO": "PCX",
    "ATIVOS": [],
    "DATA": "2024-07-26",
    "SUBIDA": {
        "RUMO": {
            "GRAO": {
                "SALDO_VIRADA": 0,
                "SALDO_NAVEGACAO": [
                    1420,
                    1400,
                    1482,
                    1462,
                    1442,
                    1582,
                    1562,
                    1542,
                    1522,
                    1502,
                    1482,
                    1462,
                    1442,
                    1506,
                    1486,
                    1466,
                    1614,
                    1580,
                    1546,
                    1526,
                    1512,
                    1498,
                    1484,
                    1470
                ],
                "GERACAO_DE_VAZIOS": [
                    44,
                    37,
                    36,
                    19,
                    28,
                    11,
                    20,
                    20,
                    20,
                    20,
                    20,
                    20,
                    20,
                    20,
                    20,
                    20,
                    20,
                    20,
                    20,
                    20,
                    13,
                    10,
                    11,
                    8
                ],
                "GERACAO_EDITADA": [
                    0,
                    0,
                    0,
                    0,
                    0,
                    0,
                    0,
                    0,
                    0,
                    0,
                    0,
                    0,
                    0,
                    0,
                    0,
                    0,
                    0,
                    0,
                    0,
                    0,
                    0,
                    0,
                    0,
                    0
                ],
                "ALIVIO_DE_VAZIOS": [
                    64,
                    18,
                    55,
                    0,
                    47,
                    0,
                    0,
                    51,
                    0,
                    40,
                    0,
                    40,
                    0,
                    40,
                    0,
                    40,
                    0,
                    40,
                    0,
                    40,
                    0,
                    0,
                    34,
                    0
                ],
                "ALIVIO_EDITADO": [
                    0,
                    0,
                    0,
                    0,
                    0,
                    0,
                    0,
                    0,
                    0,
                    0,
                    0,
                    0,
                    0,
                    0,
                    0,
                    0,
                    0,
                    0,
                    0,
                    0,
                    0,
                    0,
                    0,
                    0
                ],
                "SALDO_DE_VAZIOS": [
                    64,
                    37,
                    55,
                    19,
                    47,
                    11,
                    31,
                    51,
                    20,
                    40,
                    20,
                    40,
                    20,
                    40,
                    20,
                    40,
                    20,
                    40,
                    20,
                    40,
                    13,
                    23,
                    34,
                    8
                ],
                "SATURACAO_VAZIO": {
                    "MIN": 0,
                    "MAX": 0
                }
            }
        },
        "MRS": {
            "GRAO": {
                "SALDO_VIRADA": 0,
                "SALDO_NAVEGACAO": [
                    0,
                    0,
                    0,
                    0,
                    0,
                    0,
                    0,
                    0,
                    0,
                    0,
                    0,
                    0,
                    0,
                    0,
                    0,
                    0,
                    0,
                    0,
                    0,
                    0,
                    0,
                    0,
                    0,
                    0
                ],
                "GERACAO_DE_VAZIOS": [
                    0,
                    0,
                    0,
                    0,
                    0,
                    0,
                    0,
                    0,
                    0,
                    0,
                    0,
                    0,
                    0,
                    0,
                    0,
                    0,
                    0,
                    0,
                    0,
                    0,
                    0,
                    0,
                    0,
                    0
                ],
                "GERACAO_EDITADA": [
                    0,
                    0,
                    0,
                    0,
                    0,
                    0,
                    0,
                    0,
                    0,
                    0,
                    0,
                    0,
                    0,
                    0,
                    0,
                    0,
                    0,
                    0,
                    0,
                    0,
                    0,
                    0,
                    0,
                    0
                ],
                "ALIVIO_DE_VAZIOS": [
                    0,
                    0,
                    0,
                    0,
                    0,
                    0,
                    0,
                    0,
                    0,
                    0,
                    0,
                    0,
                    0,
                    0,
                    0,
                    0,
                    0,
                    0,
                    0,
                    0,
                    0,
                    0,
                    0,
                    0
                ],
                "ALIVIO_EDITADO": [
                    0,
                    0,
                    0,
                    0,
                    0,
                    0,
                    0,
                    0,
                    0,
                    0,
                    0,
                    0,
                    0,
                    0,
                    0,
                    0,
                    0,
                    0,
                    0,
                    0,
                    0,
                    0,
                    0,
                    0
                ],
                "SALDO_DE_VAZIOS": [
                    0,
                    0,
                    0,
                    0,
                    0,
                    0,
                    0,
                    0,
                    0,
                    0,
                    0,
                    0,
                    0,
                    0,
                    0,
                    0,
                    0,
                    0,
                    0,
                    0,
                    0,
                    0,
                    0,
                    0
                ],
                "SATURACAO_VAZIO": {
                    "MIN": 0,
                    "MAX": 0
                }
            }
        },
        "VLI": {
            "GRAO": {
                "SALDO_VIRADA": 0,
                "SALDO_NAVEGACAO": [
                    0,
                    0,
                    0,
                    0,
                    0,
                    0,
                    0,
                    0,
                    0,
                    0,
                    0,
                    0,
                    0,
                    0,
                    0,
                    0,
                    0,
                    0,
                    0,
                    0,
                    0,
                    0,
                    0,
                    0
                ],
                "GERACAO_DE_VAZIOS": [
                    0,
                    0,
                    0,
                    0,
                    0,
                    0,
                    0,
                    0,
                    0,
                    0,
                    0,
                    0,
                    0,
                    0,
                    0,
                    0,
                    0,
                    0,
                    0,
                    0,
                    0,
                    0,
                    0,
                    0
                ],
                "GERACAO_EDITADA": [
                    0,
                    0,
                    0,
                    0,
                    0,
                    0,
                    0,
                    0,
                    0,
                    0,
                    0,
                    0,
                    0,
                    0,
                    0,
                    0,
                    0,
                    0,
                    0,
                    0,
                    0,
                    0,
                    0,
                    0
                ],
                "ALIVIO_DE_VAZIOS": [
                    0,
                    0,
                    0,
                    0,
                    0,
                    0,
                    0,
                    0,
                    0,
                    0,
                    0,
                    0,
                    0,
                    0,
                    0,
                    0,
                    0,
                    0,
                    0,
                    0,
                    0,
                    0,
                    0,
                    0
                ],
                "ALIVIO_EDITADO": [
                    0,
                    0,
                    0,
                    0,
                    0,
                    0,
                    0,
                    0,
                    0,
                    0,
                    0,
                    0,
                    0,
                    0,
                    0,
                    0,
                    0,
                    0,
                    0,
                    0,
                    0,
                    0,
                    0,
                    0
                ],
                "SALDO_DE_VAZIOS": [
                    0,
                    0,
                    0,
                    0,
                    0,
                    0,
                    0,
                    0,
                    0,
                    0,
                    0,
                    0,
                    0,
                    0,
                    0,
                    0,
                    0,
                    0,
                    0,
                    0,
                    0,
                    0,
                    0,
                    0
                ],
                "SATURACAO_VAZIO": {
                    "MIN": 0,
                    "MAX": 0
                }
            }
        }
    }
}