{
    "NOME": "",
    "PATIO": "",
    "ATIVOS": [],
    "DATA": "",
    "SUBIDA": {
        "RUMO": {
            "GRAO": {
                "SALDO_VIRADA": 0,
                "GERACAO_DE_VAZIOS": [
                    0,
                    0,
                    0,
                    45,
                    31,
                    0,
                    6,
                    33,
                    44,
                    0,
                    2,
                    0,
                    0,
                    33,
                    49,
                    0,
                    33,
                    47,
                    2,
                    33,
                    0,
                    0,
                    33,
                    16
                ],
                "GERACAO_EDITADA": [
                    0,
                    0,
                    0,
                    0,
                    0,
                    0,
                    0,
                    0,
                    0,
                    0,
                    0,
                    0,
                    0,
                    0,
                    0,
                    0,
                    0,
                    0,
                    0,
                    0,
                    0,
                    0,
                    0,
                    0
                ],
                "ALIVIO_DE_VAZIOS": [
                    0,
                    0,
                    0,
                    0,
                    0,
                    0,
                    82,
                    0,
                    0,
                    0,
                    79,
                    0,
                    0,
                    0,
                    82,
                    0,
                    0,
                    0,
                    82,
                    0,
                    0,
                    0,
                    0,
                    82
                ],
                "ALIVIO_EDITADO": [
                    0,
                    0,
                    0,
                    0,
                    0,
                    0,
                    0,
                    0,
                    0,
                    0,
                    0,
                    0,
                    0,
                    0,
                    0,
                    0,
                    0,
                    0,
                    0,
                    0,
                    0,
                    0,
                    0,
                    0
                ],
                "SALDO_DE_VAZIOS": [
                    0,
                    0,
                    0,
                    45,
                    76,
                    76,
                    82,
                    33,
                    77,
                    77,
                    79,
                    0,
                    0,
                    33,
                    82,
                    0,
                    33,
                    80,
                    82,
                    33,
                    33,
                    33,
                    66,
                    82
                ],
                "SATURACAO": {
                    "MIN": 0,
                    "MAX": 0
                }
            }
        },
        "MRS": {
            "GRAO": {
                "SALDO_VIRADA": 0,
                "GERACAO_DE_VAZIOS": [
                    0,
                    0,
                    0,
                    0,
                    0,
                    0,
                    0,
                    0,
                    0,
                    0,
                    0,
                    0,
                    0,
                    0,
                    0,
                    0,
                    0,
                    0,
                    0,
                    0,
                    0,
                    0,
                    0,
                    0
                ],
                "GERACAO_EDITADA": [
                    0,
                    0,
                    0,
                    0,
                    0,
                    0,
                    0,
                    0,
                    0,
                    0,
                    0,
                    0,
                    0,
                    0,
                    0,
                    0,
                    0,
                    0,
                    0,
                    0,
                    0,
                    0,
                    0,
                    0
                ],
                "ALIVIO_DE_VAZIOS": [
                    0,
                    0,
                    0,
                    0,
                    0,
                    0,
                    0,
                    0,
                    0,
                    0,
                    0,
                    0,
                    0,
                    0,
                    0,
                    0,
                    0,
                    0,
                    0,
                    0,
                    0,
                    0,
                    0,
                    0
                ],
                "ALIVIO_EDITADO": [
                    0,
                    0,
                    0,
                    0,
                    0,
                    0,
                    0,
                    0,
                    0,
                    0,
                    0,
                    0,
                    0,
                    0,
                    0,
                    0,
                    0,
                    0,
                    0,
                    0,
                    0,
                    0,
                    0,
                    0
                ],
                "SALDO_DE_VAZIOS": [
                    0,
                    0,
                    0,
                    0,
                    0,
                    0,
                    0,
                    0,
                    0,
                    0,
                    0,
                    0,
                    0,
                    0,
                    0,
                    0,
                    0,
                    0,
                    0,
                    0,
                    0,
                    0,
                    0,
                    0
                ],
                "SATURACAO": {
                    "MIN": 0,
                    "MAX": 0
                }
            }
        },
        "VLI": {
            "GRAO": {
                "SALDO_VIRADA": 0,
                "GERACAO_DE_VAZIOS": [
                    0,
                    0,
                    0,
                    0,
                    0,
                    0,
                    0,
                    0,
                    0,
                    0,
                    0,
                    0,
                    0,
                    0,
                    0,
                    0,
                    0,
                    0,
                    0,
                    0,
                    0,
                    0,
                    0,
                    0
                ],
                "GERACAO_EDITADA": [
                    0,
                    0,
                    0,
                    0,
                    0,
                    0,
                    0,
                    0,
                    0,
                    0,
                    0,
                    0,
                    0,
                    0,
                    0,
                    0,
                    0,
                    0,
                    0,
                    0,
                    0,
                    0,
                    0,
                    0
                ],
                "ALIVIO_DE_VAZIOS": [
                    0,
                    0,
                    0,
                    0,
                    0,
                    0,
                    0,
                    0,
                    0,
                    0,
                    0,
                    0,
                    0,
                    0,
                    0,
                    0,
                    0,
                    0,
                    0,
                    0,
                    0,
                    0,
                    0,
                    0
                ],
                "ALIVIO_EDITADO": [
                    0,
                    0,
                    0,
                    0,
                    0,
                    0,
                    0,
                    0,
                    0,
                    0,
                    0,
                    0,
                    0,
                    0,
                    0,
                    0,
                    0,
                    0,
                    0,
                    0,
                    0,
                    0,
                    0,
                    0
                ],
                "SALDO_DE_VAZIOS": [
                    0,
                    0,
                    0,
                    0,
                    0,
                    0,
                    0,
                    0,
                    0,
                    0,
                    0,
                    0,
                    0,
                    0,
                    0,
                    0,
                    0,
                    0,
                    0,
                    0,
                    0,
                    0,
                    0,
                    0
                ],
                "SATURACAO": {
                    "MIN": 0,
                    "MAX": 0
                }
            }
        }
    },
    "OCUPACAO": {
        "FERROVIA": [
            "",
            "",
            "",
            "RUMO",
            "RUMO",
            "RUMO",
            "",
            "RUMO",
            "RUMO",
            "RUMO",
            "",
            "",
            "",
            "RUMO",
            "",
            "",
            "RUMO",
            "RUMO",
            "",
            "RUMO",
            "RUMO",
            "RUMO",
            "RUMO",
            ""
        ],
        "SEGMENTO": [
            "",
            "",
            "",
            "GRAO",
            "GRAO",
            "GRAO",
            "",
            "GRAO",
            "GRAO",
            "GRAO",
            "",
            "",
            "",
            "GRAO",
            "",
            "",
            "GRAO",
            "GRAO",
            "",
            "GRAO",
            "GRAO",
            "GRAO",
            "GRAO",
            ""
        ],
        "LOTE_COMPLETO": [
            false,
            false,
            false,
            false,
            false,
            false,
            false,
            false,
            false,
            false,
            false,
            false,
            false,
            false,
            false,
            false,
            false,
            false,
            false,
            false,
            false,
            false,
            false,
            false
        ]
    }
}